mechmat/__init__.py
mechmat/material.py
mechmat/polymer.py
mechmat/core/__init__.py
mechmat/core/bibliography.py
mechmat/core/chainable.py
mechmat/core/errors.py
mechmat/principal/__init__.py
mechmat/principal/core.py
mechmat/principal/crossarrhenius.py
mechmat/principal/crosswlf.py
mechmat/principal/density.py
mechmat/principal/geometry.py
mechmat/principal/shear_rate.py
mechmat/principal/specific_weight.py
mechmat/principal/thermal.py
mechmat/principal/thermal_polymer.py
mechmat/principal/twodomaintaitpvt.py
mechmat/properties/__init__.py
mechmat/properties/elastic_deformation/__init__.py
mechmat/properties/flow/__init__.py
mechmat/properties/flow/flow.py
mechmat/properties/flow/mass_flow.py
mechmat/properties/flow/volume_flow.py
mechmat/properties/geometry/__init__.py
mechmat/properties/geometry/geometry.py
mechmat/properties/geometry/surface.py
mechmat/properties/geometry/vector.py
mechmat/properties/geometry/volume.py
mechmat/properties/mass/__init__.py
mechmat/properties/mass/mass.py
mechmat/properties/plastic_deformation/__init__.py
mechmat/properties/pressure/__init__.py
mechmat/properties/pressure/pressure.py
mechmat/properties/shearing/__init__.py
mechmat/properties/shearing/shearing.py
mechmat/properties/specific_volume/__init__.py
mechmat/properties/specific_volume/twodomaintaitpvt.py
mechmat/properties/thermal/__init__.py
mechmat/properties/thermal/conductivity.py
mechmat/properties/thermal/polymer.py
mechmat/properties/thermal/thermal.py
mechmat/properties/viscosity/__init__.py
mechmat/properties/viscosity/crossarrhenius.py
mechmat/properties/viscosity/crosswlf.py
mechmat/properties/viscosity/viscosity.py
mechmat/resources/sources.bib
mechmat-0.2.4.dist-info/AUTHORS.rst
mechmat-0.2.4.dist-info/LICENSE
mechmat-0.2.4.dist-info/METADATA
mechmat-0.2.4.dist-info/WHEEL
mechmat-0.2.4.dist-info/top_level.txt
mechmat-0.2.4.dist-info/RECORD
