Metadata-Version: 2.1
Name: mechmat
Version: 0.2.4
Summary: Python package for the definition of materials used during mechanical engineering calculations
Home-page: https://github.com/mecheng/mechmat
Author: Jelle Spijker
Author-email: spijker.jelle@gmail.com
License: MIT license
Keywords: mechmat
Platform: UNKNOWN
Classifier: Development Status :: 2 - Pre-Alpha
Classifier: Intended Audience :: Developers
Classifier: License :: OSI Approved :: MIT License
Classifier: Natural Language :: English
Classifier: Programming Language :: Python :: 3
Classifier: Programming Language :: Python :: 3.4
Classifier: Programming Language :: Python :: 3.5
Classifier: Programming Language :: Python :: 3.6
Classifier: Programming Language :: Python :: 3.7
Requires-Dist: pint
Requires-Dist: numpy
Requires-Dist: dill
Requires-Dist: pytablewriter
Requires-Dist: dominate
Requires-Dist: mechcite
Requires-Dist: scipy
